pydantic_appconfig/__init__.py
pydantic_appconfig/app_config.py
pydantic_appconfig/py.typed
pydantic_appconfig-2.0.0.dist-info/LICENSE
pydantic_appconfig-2.0.0.dist-info/METADATA
pydantic_appconfig-2.0.0.dist-info/WHEEL
pydantic_appconfig-2.0.0.dist-info/RECORD
