Metadata-Version: 2.1
Name: pydantic-appconfig
Version: 2.0.0
Summary: Helper package for using AWS App Config with Pydantic
Home-page: https://github.com/Validus-Risk-Management/aws-appconfig-pydantic
Author: Validus Tech Team
Author-email: techteam@validusrm.com
Requires-Python: >=3.8,<4.0
Classifier: Programming Language :: Python :: 3
Classifier: Programming Language :: Python :: 3.8
Classifier: Programming Language :: Python :: 3.9
Classifier: Programming Language :: Python :: 3.10
Classifier: Programming Language :: Python :: 3.11
Requires-Dist: PyYAML (>=6.0,<7.0)
Requires-Dist: boto3 (>=1.20.8,<2.0.0)
Requires-Dist: botocore (>=1.23.8,<2.0.0)
Requires-Dist: pydantic (>=2.0.3,<3.0.0)
Project-URL: Repository, https://github.com/Validus-Risk-Management/aws-appconfig-pydantic
